tuple_list_benchmark/base.py
tuple_list_benchmark/bench.py
tuple_list_benchmark/test-list.py
tuple_list_benchmark/test-tuple.py
tuple_list_benchmark-0.1.0.dist-info/METADATA
tuple_list_benchmark-0.1.0.dist-info/WHEEL
tuple_list_benchmark-0.1.0.dist-info/entry_points.txt
tuple_list_benchmark-0.1.0.dist-info/top_level.txt
tuple_list_benchmark-0.1.0.dist-info/RECORD
