Metadata-Version: 2.4
Name: tuple-list-benchmark
Version: 0.1.0
Summary: Add your description here
Requires-Python: >=3.8
Requires-Dist: pyperf
Requires-Dist: tyro>=1.0.2
